marqeta/__init__.py
marqeta/errors.py
marqeta/version.py
marqeta/resources/__init__.py
marqeta/resources/accepted_countries.py
marqeta/resources/account_holder_groups.py
marqeta/resources/auth_controls.py
marqeta/resources/auto_reloads.py
marqeta/resources/balances.py
marqeta/resources/bulk_issuances.py
marqeta/resources/businesses.py
marqeta/resources/card_products.py
marqeta/resources/cards.py
marqeta/resources/chargebacks.py
marqeta/resources/collection.py
marqeta/resources/commando_modes.py
marqeta/resources/digital_wallet_tokens.py
marqeta/resources/direct_deposits.py
marqeta/resources/fee_transfers.py
marqeta/resources/fees.py
marqeta/resources/funding_sources.py
marqeta/resources/gpa_orders.py
marqeta/resources/kyc.py
marqeta/resources/mcc_groups.py
marqeta/resources/merchants.py
marqeta/resources/msa_orders.py
marqeta/resources/offer_orders.py
marqeta/resources/pins.py
marqeta/resources/program_transfers.py
marqeta/resources/push_to_cards.py
marqeta/resources/real_time_fee_groups.py
marqeta/resources/transactions.py
marqeta/resources/users.py
marqeta/resources/velocity_controls.py
marqeta/resources/webhooks.py
marqeta/response_models/__init__.py
marqeta/response_models/accepted_countries_model.py
marqeta/response_models/accepted_countries_update_model.py
marqeta/response_models/access_token_response.py
marqeta/response_models/account.py
marqeta/response_models/account_holder_group_config.py
marqeta/response_models/account_holder_group_request.py
marqeta/response_models/account_holder_group_response.py
marqeta/response_models/account_holder_group_update_request.py
marqeta/response_models/account_model.py
marqeta/response_models/ach_model.py
marqeta/response_models/ach_response_model.py
marqeta/response_models/ach_return.py
marqeta/response_models/ach_reversal_request.py
marqeta/response_models/ach_verification_model.py
marqeta/response_models/acquirer.py
marqeta/response_models/activation_actions.py
marqeta/response_models/address_request_model.py
marqeta-0.2.1.dist-info/LICENSE
marqeta-0.2.1.dist-info/METADATA
marqeta-0.2.1.dist-info/WHEEL
marqeta-0.2.1.dist-info/top_level.txt
marqeta-0.2.1.dist-info/RECORD
