Metadata-Version: 2.1
Name: marqeta
Version: 0.2.1
Summary: Marqeta Python SDK
Home-page: https://github.com/marqeta/marqeta-python
Author: Marqeta, Inc.
License: MIT
Project-URL: Documentation, https://marqeta.com/api
Project-URL: Source Code, https://github.com/marqeta/marqeta-python
Keywords: marqeta
Platform: UNKNOWN
Classifier: Development Status :: 4 - Beta
Classifier: Intended Audience :: Developers
Classifier: License :: OSI Approved :: MIT License
Classifier: Programming Language :: Python :: 3
Classifier: Programming Language :: Python :: 3.7
Classifier: Topic :: Software Development :: Libraries :: Python Modules
Requires-Dist: requests (>=2.0.0)
Requires-Dist: pytz (>=2019.1)
Requires-Dist: faker (>=1.0.7)
